face_projection/__init__.py
face_projection/core.py
face_projection/emotion_landmarks.h5
face_projection/face_model.h5
face_projection-1.1.1.dist-info/LICENSE.txt
face_projection-1.1.1.dist-info/METADATA
face_projection-1.1.1.dist-info/WHEEL
face_projection-1.1.1.dist-info/top_level.txt
face_projection-1.1.1.dist-info/RECORD
