Metadata-Version: 2.1
Name: face-projection
Version: 1.1.1
Summary: This projects main goal is to have a simple library to project information into faces while retaining the facial structure.
Home-page: https://github.com/pyscaffold/pyscaffold/
Author: Tim Büchner
Author-email: tim.buechner@uni-jena.de
License: MIT
Project-URL: Source, https://github.com/cvjena/face-projection
Project-URL: Tracker, https://github.com/cvjena/face-projection/issues
Platform: any
Classifier: Development Status :: 5 - Production/Stable
Classifier: Programming Language :: Python
Requires-Python: >=3.9
License-File: LICENSE.txt
Requires-Dist: numpy
Requires-Dist: meshpy
Requires-Dist: opencv-python-headless
Requires-Dist: h5py >=3.10
Requires-Dist: mediapipe ==0.9.3.0 ; platform_system != "Darwin" or platform_machine != "arm64"
Requires-Dist: mediapipe-silicon ==0.9.2.1 ; platform_system == "Darwin" and platform_machine == "arm64"
Provides-Extra: testing
Requires-Dist: setuptools ; extra == 'testing'
Requires-Dist: pytest ; extra == 'testing'
Requires-Dist: pytest-cov ; extra == 'testing'
